<?xml version="1.0" encoding="utf-8" ?>
<dwsync>
<file name="Dugan2010ACS.jpg" server="10.0.3.2//var/www/html/" local="129860177568202500" remote="131069746650000000" Dst="2" />
<file name="SaraWichner2010ACS.jpg" server="10.0.3.2//var/www/html/" local="129860177434921250" remote="131069746690000000" Dst="2" />
<file name="QIQC.png" server="10.0.3.2//var/www/html/" local="129897025247675000" remote="131069746690000000" Dst="2" />
<file name="SaraWichner2010ACS.jpg" server="10.0.3.2//var/www/html/new/" local="129860177434921250" remote="131066725280000000" Dst="2" />
<file name="QIQC.png" server="10.0.3.2//var/www/html/new/" local="129897025247675000" remote="131066725270000000" Dst="2" />
<file name="Dugan2010ACS.jpg" server="10.0.3.2//var/www/html/new/" local="129860177568202500" remote="131066725270000000" Dst="2" />
<file name="NickLewisGraduation.jpg" server="engelgroup.uchicago.edu//var/www/html/new/" local="129837688521875000" remote="129844654880000000" Dst="-1" />
<file name="PhotoWithPhoenix.jpg" server="engelgroup.uchicago.edu//var/www/html/new/" local="129837688752187500" remote="129844654880000000" Dst="-1" />
<file name="SolvayPhoto.jpg" server="engelgroup.uchicago.edu//var/www/html/new/" local="129369132445625000" remote="129844654880000000" Dst="-1" />
<file name="NickLewisGraduation.jpg" server="engelgroup.uchicago.edu//var/www/html/" local="129837688521875000" remote="129856483690000000" Dst="-1" />
<file name="PhotoWithPhoenix.jpg" server="engelgroup.uchicago.edu//var/www/html/" local="129837688752187500" remote="129856483690000000" Dst="-1" />
<file name="SolvayPhoto.jpg" server="engelgroup.uchicago.edu//var/www/html/" local="129369132445625000" remote="129856483690000000" Dst="-1" />
<file name="NickLewisGraduation.jpg" server="10.0.3.2//var/www/html/" local="129837688521875000" remote="131069746690000000" Dst="2" />
<file name="PhotoWithPhoenix.jpg" server="10.0.3.2//var/www/html/" local="129837688752187500" remote="131069746690000000" Dst="2" />
<file name="SolvayPhoto.jpg" server="10.0.3.2//var/www/html/" local="129369132445625000" remote="131069746690000000" Dst="2" />
<file name="Dugan2010ACS.jpg" server="engelgroup.uchicago.edu//var/www/html/" local="129860177568202500" remote="129895223850000000" Dst="-1" />
<file name="QIQC.png" server="engelgroup.uchicago.edu//var/www/html/" local="129897025247675000" remote="129897025350000000" Dst="-1" />
<file name="SaraWichner2010ACS.jpg" server="engelgroup.uchicago.edu//var/www/html/" local="129860177434921250" remote="129895223850000000" Dst="-1" />
<file name="GittDefense.jpg" server="engelgroup.uchicago.edu//var/www/html/" local="129883854171353750" remote="129883855180000000" Dst="-1" />
<file name="GregKelly.jpg" server="engelgroup.uchicago.edu//var/www/html/" local="129895222288977500" remote="129895223850000000" Dst="-1" />
<file name="GregKelly.jpg" server="10.0.3.2//var/www/html/" local="129895222288977500" remote="131069746670000000" Dst="2" />
<file name="GittDefense.jpg" server="10.0.3.2//var/www/html/" local="129883854171353750" remote="131069746660000000" Dst="2" />
<file name="LaneTribune.jpg" server="10.0.3.2//var/www/html/" local="130035964244177607" remote="131069746680000000" Dst="2" />
<file name="LaneAtIntelSTSwithArneDuncan.jpg" server="10.0.3.2//var/www/html/" local="130107653064179940" remote="131069746680000000" Dst="2" />
<file name="LaneAtIntelSTS1.jpg" server="10.0.3.2//var/www/html/" local="130107653485361739" remote="131069746680000000" Dst="2" />
<file name="HayesScience1.jpg" server="10.0.3.2//var/www/html/" local="130107656383860362" remote="131069746670000000" Dst="2" />
<file name="HayesScience2.jpg" server="10.0.3.2//var/www/html/" local="130107656685676248" remote="131069746670000000" Dst="2" />
<file name="Caram.jpg" server="10.0.3.2//var/www/html/" local="130162318716610642" remote="131069746650000000" Dst="2" />
<file name="FidlerDefense.JPG" server="10.0.3.2//var/www/html/" local="130166418559991146" remote="131069746660000000" Dst="2" />
<file name="PhilGraduation.jpg" server="10.0.3.2//var/www/html/" local="130184586181828402" remote="131069746690000000" Dst="2" />
<file name="KenleyPelzerBabyGirl.jpg" server="10.0.3.2//var/www/html/" local="130378160782681741" remote="131069746680000000" Dst="2" />
<file name="2014BabyShower.jpg" server="10.0.3.2//var/www/html/" local="130449812966222729" remote="131069746630000000" Dst="2" />
<file name="Evan.jpg" server="10.0.3.2//var/www/html/" local="130492190126791600" remote="131069746660000000" Dst="2" />
<file name="KenleyDefense.jpg" server="10.0.3.2//var/www/html/" local="130492189757256433" remote="131069746680000000" Dst="2" />
<file name="2014BabyShower.jpg" server="10.0.3.2//var/www/html/new/" local="130449812966222729" remote="131066725270000000" Dst="2" />
<file name="Caram.jpg" server="10.0.3.2//var/www/html/new/" local="130162318716610642" remote="131066725270000000" Dst="2" />
<file name="Evan.jpg" server="10.0.3.2//var/www/html/new/" local="130492190126791600" remote="131066725270000000" Dst="2" />
<file name="FidlerDefense.JPG" server="10.0.3.2//var/www/html/new/" local="130166418559991146" remote="131066725270000000" Dst="2" />
<file name="GittDefense.jpg" server="10.0.3.2//var/www/html/new/" local="129883854171353750" remote="131066725270000000" Dst="2" />
<file name="GregKelly.jpg" server="10.0.3.2//var/www/html/new/" local="129895222288977500" remote="131066725270000000" Dst="2" />
<file name="HayesScience1.jpg" server="10.0.3.2//var/www/html/new/" local="130107656383860362" remote="131066725270000000" Dst="2" />
<file name="HayesScience2.jpg" server="10.0.3.2//var/www/html/new/" local="130107656685676248" remote="131066725270000000" Dst="2" />
<file name="KenleyDefense.jpg" server="10.0.3.2//var/www/html/new/" local="130492189757256433" remote="131066725270000000" Dst="2" />
<file name="KenleyPelzerBabyGirl.jpg" server="10.0.3.2//var/www/html/new/" local="130378160782681741" remote="131066725270000000" Dst="2" />
<file name="LaneAtIntelSTS1.jpg" server="10.0.3.2//var/www/html/new/" local="130107653485361739" remote="131066725270000000" Dst="2" />
<file name="LaneAtIntelSTSwithArneDuncan.jpg" server="10.0.3.2//var/www/html/new/" local="130107653064179940" remote="131066725270000000" Dst="2" />
<file name="LaneTribune.jpg" server="10.0.3.2//var/www/html/new/" local="130035964244177607" remote="131066725270000000" Dst="2" />
<file name="NickLewisGraduation.jpg" server="10.0.3.2//var/www/html/new/" local="129837688521875000" remote="131066725270000000" Dst="2" />
<file name="PhilGraduation.jpg" server="10.0.3.2//var/www/html/new/" local="130184586181828402" remote="131066725270000000" Dst="2" />
<file name="PhotoWithPhoenix.jpg" server="10.0.3.2//var/www/html/new/" local="129837688752187500" remote="131066725270000000" Dst="2" />
<file name="SolvayPhoto.jpg" server="10.0.3.2//var/www/html/new/" local="129369132445625000" remote="131066725280000000" Dst="2" />
<file name="Engel.JPG" server="10.0.3.2//var/www/html/new/" local="129103059993142500" remote="131067568260000000" Dst="2" />
<file name="P011310LJ-0022.jpg" server="10.0.3.2//var/www/html/new/" local="129103059679861250" remote="131067568260000000" Dst="2" />
<file name="Engel.JPG" server="10.0.3.2//var/www/html/" local="129103059993142500" remote="131069746660000000" Dst="2" />
<file name="P011310LJ-0022.jpg" server="10.0.3.2//var/www/html/" local="129103059679861250" remote="131069746690000000" Dst="2" />
<file name="VedGraduation.jpg" server="10.0.3.2//var/www/html/" local="131076168881046747" remote="131076172290000000" Dst="2" />
<file name="BentonJim1.jpg" server="10.0.3.2//var/www/html/" local="131109284132580615" remote="131109291300000000" Dst="2" />
<file name="BentonJim2.jpg" server="10.0.3.2//var/www/html/" local="131109284140930642" remote="131109291300000000" Dst="2" />
<file name="BentonJim3.jpg" server="10.0.3.2//var/www/html/" local="131109284151580806" remote="131109291310000000" Dst="2" />
<file name="DahlbergDefense.jpg" server="10.0.3.2//var/www/html/" local="131142704155314678" remote="131142707250000000" Dst="2" />
<file name="PHYS.png" server="10.0.3.2//var/www/html/" local="131166891829215234" remote="131168005190000000" Dst="2" />
<file name="MoiraGraduation.jpg" server="10.0.3.2//var/www/html/" local="131172994930785090" remote="131172997720000000" Dst="2" />
</dwsync>